semantic_eq_client/__init__.py
semantic_eq_client/client.py
semantic_eq_client/models.py
semantic_eq-1.0.6.dist-info/METADATA
semantic_eq-1.0.6.dist-info/WHEEL
semantic_eq-1.0.6.dist-info/top_level.txt
semantic_eq-1.0.6.dist-info/RECORD
